base/__init__.py
base/__main__.py
base/classmodule.py
base/drawmodule.py
base/funcmodule.py
PStock-0.0.1.dist-info/METADATA
PStock-0.0.1.dist-info/WHEEL
PStock-0.0.1.dist-info/entry_points.txt
PStock-0.0.1.dist-info/top_level.txt
PStock-0.0.1.dist-info/RECORD
